{
    "tag_code": "t16h5",
    "cols": 11,
    "rows": 11,
    "board": {
        "0": {
            "0": {
                "id": 1,
                "board_x": 3,
                "board_y": 8
            },
            "1": {
                "id": 2,
                "board_x": 5,
                "board_y": 8
            },
            "2": {
                "id": 3,
                "board_x": 3,
                "board_y": 6
            },
            "3": {
                "id": 4,
                "board_x": 5,
                "board_y": 6
            },
            "4": {
                "id": 7,
                "board_x": 5,
                "board_y": 4
            },
            "5": {
                "id": 8,
                "board_x": 7,
                "board_y": 4
            },
            "6": {
                "id": 9,
                "board_x": 5,
                "board_y": 2
            },
            "7": {
                "id": 10,
                "board_x": 7,
                "board_y": 2
            }
        }
    },
    "corner3d": {
        "0": {
            "b": 0,
            "row": 1,
            "col": 5,
            "x": 0.0,
            "y": 0.0,
            "z": 0.0
        },
        "1": {
            "b": 0,
            "row": 1,
            "col": 6,
            "x": 30.0,
            "y": 0.0,
            "z": 0.0
        },
        "2": {
            "b": 0,
            "row": 1,
            "col": 7,
            "x": 60.0,
            "y": 0.0,
            "z": 0.0
        },
        "3": {
            "b": 0,
            "row": 1,
            "col": 8,
            "x": 90.0,
            "y": 0.0,
            "z": 0.0
        },
        "4": {
            "b": 0,
            "row": 1,
            "col": 9,
            "x": 120.0,
            "y": 0.0,
            "z": 0.0
        },
        "5": {
            "b": 0,
            "row": 2,
            "col": 5,
            "x": 15.0,
            "y": -25.980762113533157,
            "z": 0.0
        },
        "6": {
            "b": 0,
            "row": 2,
            "col": 6,
            "x": 45.0,
            "y": -25.980762113533157,
            "z": 0.0
        },
        "7": {
            "b": 0,
            "row": 2,
            "col": 7,
            "x": 75.0,
            "y": -25.980762113533157,
            "z": 0.0
        },
        "8": {
            "b": 0,
            "row": 2,
            "col": 8,
            "x": 105.0,
            "y": -25.980762113533157,
            "z": 0.0
        },
        "9": {
            "b": 0,
            "row": 2,
            "col": 9,
            "x": 135.0,
            "y": -25.980762113533157,
            "z": 0.0
        },
        "10": {
            "b": 0,
            "row": 3,
            "col": 4,
            "x": 0.0,
            "y": -51.96152422706631,
            "z": 0.0
        },
        "11": {
            "b": 0,
            "row": 3,
            "col": 5,
            "x": 30.0,
            "y": -51.96152422706631,
            "z": 0.0
        },
        "12": {
            "b": 0,
            "row": 3,
            "col": 6,
            "x": 60.0,
            "y": -51.96152422706631,
            "z": 0.0
        },
        "13": {
            "b": 0,
            "row": 3,
            "col": 7,
            "x": 90.0,
            "y": -51.96152422706631,
            "z": 0.0
        },
        "14": {
            "b": 0,
            "row": 3,
            "col": 8,
            "x": 120.0,
            "y": -51.96152422706631,
            "z": 0.0
        },
        "15": {
            "b": 0,
            "row": 4,
            "col": 4,
            "x": 15.0,
            "y": -77.94228634059948,
            "z": 0.0
        },
        "16": {
            "b": 0,
            "row": 4,
            "col": 5,
            "x": 45.0,
            "y": -77.94228634059948,
            "z": 0.0
        },
        "17": {
            "b": 0,
            "row": 4,
            "col": 6,
            "x": 75.0,
            "y": -77.94228634059948,
            "z": 0.0
        },
        "18": {
            "b": 0,
            "row": 4,
            "col": 7,
            "x": 105.0,
            "y": -77.94228634059948,
            "z": 0.0
        },
        "19": {
            "b": 0,
            "row": 4,
            "col": 8,
            "x": 135.0,
            "y": -77.94228634059948,
            "z": 0.0
        },
        "20": {
            "b": 0,
            "row": 5,
            "col": 3,
            "x": 0.0,
            "y": -103.92304845413263,
            "z": 0.0
        },
        "21": {
            "b": 0,
            "row": 5,
            "col": 4,
            "x": 30.0,
            "y": -103.92304845413263,
            "z": 0.0
        },
        "22": {
            "b": 0,
            "row": 5,
            "col": 5,
            "x": 60.0,
            "y": -103.92304845413263,
            "z": 0.0
        },
        "23": {
            "b": 0,
            "row": 5,
            "col": 6,
            "x": 90.0,
            "y": -103.92304845413263,
            "z": 0.0
        },
        "24": {
            "b": 0,
            "row": 5,
            "col": 7,
            "x": 120.0,
            "y": -103.92304845413263,
            "z": 0.0
        },
        "25": {
            "b": 0,
            "row": 6,
            "col": 3,
            "x": 15.0,
            "y": -129.9038105676658,
            "z": 0.0
        },
        "26": {
            "b": 0,
            "row": 6,
            "col": 4,
            "x": 45.0,
            "y": -129.9038105676658,
            "z": 0.0
        },
        "27": {
            "b": 0,
            "row": 6,
            "col": 5,
            "x": 75.0,
            "y": -129.9038105676658,
            "z": 0.0
        },
        "28": {
            "b": 0,
            "row": 6,
            "col": 6,
            "x": 105.0,
            "y": -129.9038105676658,
            "z": 0.0
        },
        "29": {
            "b": 0,
            "row": 6,
            "col": 7,
            "x": 135.0,
            "y": -129.9038105676658,
            "z": 0.0
        },
        "30": {
            "b": 0,
            "row": 7,
            "col": 2,
            "x": 0.0,
            "y": -155.88457268119896,
            "z": 0.0
        },
        "31": {
            "b": 0,
            "row": 7,
            "col": 3,
            "x": 30.0,
            "y": -155.88457268119896,
            "z": 0.0
        },
        "32": {
            "b": 0,
            "row": 7,
            "col": 4,
            "x": 60.0,
            "y": -155.88457268119896,
            "z": 0.0
        },
        "33": {
            "b": 0,
            "row": 7,
            "col": 5,
            "x": 90.0,
            "y": -155.88457268119896,
            "z": 0.0
        },
        "34": {
            "b": 0,
            "row": 7,
            "col": 6,
            "x": 120.0,
            "y": -155.88457268119896,
            "z": 0.0
        },
        "35": {
            "b": 0,
            "row": 8,
            "col": 2,
            "x": 15.0,
            "y": -181.8653347947321,
            "z": 0.0
        },
        "36": {
            "b": 0,
            "row": 8,
            "col": 3,
            "x": 45.0,
            "y": -181.8653347947321,
            "z": 0.0
        },
        "37": {
            "b": 0,
            "row": 8,
            "col": 4,
            "x": 75.0,
            "y": -181.8653347947321,
            "z": 0.0
        },
        "38": {
            "b": 0,
            "row": 8,
            "col": 5,
            "x": 105.0,
            "y": -181.8653347947321,
            "z": 0.0
        },
        "39": {
            "b": 0,
            "row": 8,
            "col": 6,
            "x": 135.0,
            "y": -181.8653347947321,
            "z": 0.0
        },
        "40": {
            "b": 0,
            "row": 9,
            "col": 1,
            "x": 0.0,
            "y": -207.84609690826525,
            "z": 0.0
        },
        "41": {
            "b": 0,
            "row": 9,
            "col": 2,
            "x": 30.0,
            "y": -207.84609690826525,
            "z": 0.0
        },
        "42": {
            "b": 0,
            "row": 9,
            "col": 3,
            "x": 60.0,
            "y": -207.84609690826525,
            "z": 0.0
        },
        "43": {
            "b": 0,
            "row": 9,
            "col": 4,
            "x": 90.0,
            "y": -207.84609690826525,
            "z": 0.0
        },
        "44": {
            "b": 0,
            "row": 9,
            "col": 5,
            "x": 120.0,
            "y": -207.84609690826525,
            "z": 0.0
        },
        "45": {
            "b": 0,
            "row": 10,
            "col": 1,
            "x": 15.0,
            "y": -233.8268590217984,
            "z": 0.0
        },
        "46": {
            "b": 0,
            "row": 10,
            "col": 2,
            "x": 45.0,
            "y": -233.8268590217984,
            "z": 0.0
        },
        "47": {
            "b": 0,
            "row": 10,
            "col": 3,
            "x": 75.0,
            "y": -233.8268590217984,
            "z": 0.0
        },
        "48": {
            "b": 0,
            "row": 10,
            "col": 4,
            "x": 105.0,
            "y": -233.8268590217984,
            "z": 0.0
        },
        "49": {
            "b": 0,
            "row": 10,
            "col": 5,
            "x": 135.0,
            "y": -233.8268590217984,
            "z": 0.0
        }
    }
}